{
  "node": "rohit-janardhan-VirtualBox",
  "hostname": "rohit-janardhan-VirtualBox",
  "metrics": {
    "cpu": 4.9,
    "memory": 60.1,
    "disk": 99.25714285714285,
    "processes": [
      {
        "pid": 11254,
        "name": "python3",
        "cpu": 41.8,
        "memory": 3.23
      },
      {
        "pid": 4905,
        "name": "Isolated Web Co",
        "cpu": 29.2,
        "memory": 41.84
      },
      {
        "pid": 2742,
        "name": "gnome-shell",
        "cpu": 22.5,
        "memory": 1.25
      },
      {
        "pid": 4133,
        "name": "firefox",
        "cpu": 11.4,
        "memory": 1.28
      },
      {
        "pid": 3854,
        "name": "uvicorn",
        "cpu": 0.8,
        "memory": 0.16
      }
    ],
    "network": {
      "bytes_sent": 4419667,
      "bytes_recv": 6770087,
      "throughput": 4.419667
    },
    "disk_io": {
      "read_bytes": 29434133504,
      "write_bytes": 12377239552
    }
  },
  "probes": {
    "cpu": "ok",
    "memory": "ok",
    "disk": "ok"
  },
  "timestamp": "2026-03-26T14:57:01.053251+00:00"
}